pydiffchecker/__init__.py
pydiffchecker/cli.py
pydiffchecker/git_version.py
pydiffchecker/helper.py
pydiffchecker/line_shift_checker.py
pydiffchecker/version.py
pydiffchecker-0.1.5.dist-info/LICENSE.md
pydiffchecker-0.1.5.dist-info/METADATA
pydiffchecker-0.1.5.dist-info/WHEEL
pydiffchecker-0.1.5.dist-info/entry_points.txt
pydiffchecker-0.1.5.dist-info/top_level.txt
pydiffchecker-0.1.5.dist-info/RECORD
