Metadata-Version: 2.1
Name: pydiffchecker
Version: 0.1.5
Summary: Wrappers for git diff
Home-page: https://git.esoko.eu/bence/pydiffchecker.git
Author: Bence Pocze
Author-email: bence@pocze.ch
License: UNKNOWN
Platform: UNKNOWN
Requires-Python: >=3.8
License-File: LICENSE.md
